{
  "loginDetails": [
    {
      "id": 1,
      "firstName": "Tamil",
      "lastName": "Arasan",
      "phone": "8050774633",
      "email": "tamil@gmail.com",
      "password": "tamila@22!",
      "type": "admin"
    },
    {
      "id": 2,
      "firstName": "Achin",
      "lastName": "Prakash",
      "phone": "8050774233",
      "email": "achin@facebook.com",
      "password": "achin@22!",
      "type": "airlineStaff"
    },
    {
      "id": 3,
      "firstName": "Mohan",
      "lastName": "Babu",
      "phone": "8050774633",
      "email": "jmohan@gmail.com",
      "password": "November",
      "type": "airlineStaff"
    },
    {
      "id": 4,
      "firstName": "Shashi",
      "lastName": "Kumar",
      "phone": "8130201206",
      "email": "shashi@admin.com",
      "password": "admin",
      "type": "admin"
    },
    {
      "id": 5,
      "firstName": "Shashi",
      "lastName": "Kumar",
      "phone": "8130201206",
      "email": "shashi@staff.com",
      "password": "staff",
      "type": "airlineStaff"
    }
  ],
  "PassengerDetails": [
    {
      "flightId": "1",
      "first_name": "Sonia",
      "last_name": "Gandhi",
      "date_of_birth": "01/01/2018",
      "gender": "Female",
      "email_id": "sonia@manmohan.com",
      "mobile_no": "9451459777",
      "country": "IND",
      "date_of_travel": "",
      "seat_no": "4B",
      "travel_document": "5678977",
      "wheelChair": "No",
      "infant": "No",
      "status": "AC",
      "address": "Delhi,India",
      "meals": [
        "Pizza",
        "Burger",
        "Tea"
      ],
      "special_service": [
        "Window Seat",
        "Music"
      ],
      "flight_shop": [
        "Watch",
        "Walet"
      ],
      "id": 1
    },
    {
      "flightId": "1",
      "first_name": "Manmohan",
      "last_name": "singh",
      "date_of_birth": "1/2/1809",
      "gender": "Male",
      "email_id": "manmohan@sonia.com",
      "mobile_no": "9876545678",
      "country": "IND",
      "date_of_travel": "",
      "seat_no": "4C",
      "travel_document": "87654678",
      "wheelChair": "Yes",
      "infant": "No",
      "status": "AC",
      "address": "Delhi,India",
      "meals": [
        "Burger",
        "Pizza"
      ],
      "special_service": [
        "Window Seat",
        "Music",
        "TV"
      ],
      "flight_shop": [
        "Walet",
        "Watch"
      ],
      "id": 2
    },
    {
      "flightId": "1",
      "first_name": "Nitin",
      "last_name": "Gadkari",
      "date_of_birth": "01/2/1900",
      "gender": "Male",
      "email_id": "nitin@gmail.com",
      "mobile_no": "578987657",
      "country": "ind",
      "date_of_travel": "",
      "seat_no": "2C",
      "travel_document": "",
      "wheelChair": "No",
      "status": "AC",
      "meals": [],
      "special_service": [],
      "flight_shop": [],
      "address": "",
      "id": 3
    },
    {
      "flightId": "1",
      "first_name": "Sushma",
      "last_name": "Swaraj",
      "date_of_birth": "10/10/1967",
      "gender": "Female",
      "email_id": "shusma@gmail.com",
      "mobile_no": "987654789",
      "country": "ind",
      "date_of_travel": "",
      "seat_no": "1E",
      "travel_document": "",
      "wheelChair": "No",
      "infant": "No",
      "status": "AC",
      "meals": [],
      "special_service": [],
      "flight_shop": [],
      "address": "",
      "id": 4
    },
    {
      "flightId": "2",
      "first_name": "Mohan",
      "last_name": "babu",
      "date_of_birth": "23/12/1939",
      "gender": "Male",
      "email_id": "mohan@mindtree.com",
      "mobile_no": "9451459870",
      "country": "IND",
      "date_of_travel": "",
      "seat_no": "1D",
      "travel_document": "5678900",
      "wheelChair": "Yes",
      "infant": "No",
      "status": "AC",
      "meals": [
        "Pizza",
        "Burger"
      ],
      "special_service": [
        "Window Seat",
        "TV",
        "Dance"
      ],
      "flight_shop": [
        "Walet",
        "Watch"
      ],
      "address": "Lahore, IND",
      "id": 5
    },
    {
      "flightId": "3",
      "first_name": "Gouthami",
      "last_name": "P",
      "date_of_birth": "10/10/2012",
      "gender": "Female",
      "email_id": "gouthami.p@mindtree.com",
      "mobile_no": "987657897",
      "country": "ind",
      "date_of_travel": "",
      "seat_no": "-",
      "travel_document": "098765",
      "wheelChair": "No",
      "infant": "No",
      "status": "NC",
      "address": "AP, India",
      "meals": [],
      "special_service": [],
      "flight_shop": [],
      "id": 6
    },
    {
      "flightId": "1",
      "first_name": "gouthami",
      "last_name": "p",
      "date_of_birth": "02/04/2012",
      "gender": "Female",
      "email_id": "gouthami.p@mindtree.com",
      "mobile_no": "9876545678",
      "country": "ind",
      "date_of_travel": "",
      "seat_no": "9A",
      "travel_document": "9876543",
      "wheelChair": "No",
      "infant": "Yes",
      "status": "AC",
      "meals": [],
      "special_service": [],
      "flight_shop": [],
      "address": "",
      "id": 7
    },
    {
      "flightId": "1",
      "first_name": "Subham",
      "last_name": "Verma",
      "date_of_birth": "23/12/1990",
      "gender": "Male",
      "email_id": "subam@min.com",
      "mobile_no": "8765789987",
      "country": "us",
      "date_of_travel": "",
      "seat_no": "7B",
      "travel_document": "89765",
      "wheelChair": "Yes",
      "infant": "Yes",
      "status": "AC",
      "address": "indida",
      "meals": [],
      "special_service": [],
      "flight_shop": [],
      "id": 8
    },
    {
      "flightId": "1",
      "first_name": "New",
      "last_name": "passenger",
      "date_of_birth": "12/10/1990",
      "gender": "Male",
      "email_id": "new@pax.com",
      "mobile_no": "9876578987",
      "country": "Ind",
      "date_of_travel": "",
      "seat_no": "-",
      "travel_document": "8765789",
      "wheelChair": "Yes",
      "infant": "Yes",
      "status": "NC",
      "address": "Vill-India",
      "meals": [],
      "special_service": [],
      "flight_shop": [],
      "id": 9
    },
    {
      "flightId": "1",
      "first_name": "Sakhi",
      "last_name": "Saheli",
      "date_of_birth": "2/2/2020",
      "gender": "Male",
      "email_id": "sakhi@sahelli.com",
      "mobile_no": "6829152397",
      "country": "bangladesh",
      "date_of_travel": "",
      "seat_no": "-",
      "travel_document": "766567",
      "wheelChair": "Yes",
      "infant": "Yes",
      "status": "NC",
      "address": "Dhaka, Bangladesh",
      "meals": [],
      "special_service": [],
      "flight_shop": [],
      "id": 10
    },
    {
      "flightId": "1",
      "first_name": "Kalua",
      "last_name": "Gayak ji",
      "date_of_birth": "23/12/1939",
      "gender": "Male",
      "email_id": "kalua@singer.com",
      "mobile_no": "767577898",
      "country": "ind",
      "date_of_travel": "",
      "seat_no": "-",
      "travel_document": "876566",
      "infant": "Yes",
      "status": "NC",
      "address": "Bihar,ind",
      "meals": [],
      "special_service": [],
      "flight_shop": [],
      "id": 11
    },
    {
      "flightId": "1",
      "first_name": "new name",
      "last_name": "pax",
      "date_of_birth": "01/01/2018",
      "gender": "Male",
      "email_id": "shashi.kumar2@mindtree.com",
      "mobile_no": "9451459870",
      "country": "IND",
      "date_of_travel": "",
      "seat_no": "-",
      "travel_document": "",
      "status": "NC",
      "meals": [],
      "address": "Bihar,ind",
      "special_service": [],
      "flight_shop": [],
      "id": 12
    },
    {
      "flightId": "1",
      "first_name": "Man",
      "last_name": "Made",
      "date_of_birth": "12/09/1990",
      "gender": "Female",
      "email_id": "Man@gmail.com",
      "mobile_no": "9876543456",
      "country": "AUS",
      "date_of_travel": "",
      "seat_no": "1F",
      "travel_document": "",
      "wheelChair": "Yes",
      "infant": "No",
      "status": "AC",
      "meals": [],
      "special_service": [],
      "flight_shop": [],
      "address": "Bihar,ind",
      "id": 13
    },
    {
      "flightId": "2",
      "first_name": "Utsav",
      "last_name": "Singh",
      "date_of_birth": "12/10/1990",
      "gender": "Male",
      "email_id": "utsavsingh@mtree.com",
      "mobile_no": "785432566",
      "country": "ind",
      "date_of_travel": "",
      "seat_no": "4C",
      "travel_document": "5678900",
      "wheelChair": "No",
      "infant": "Yes",
      "status": "AC",
      "meals": [
        "Pizza"
      ],
      "address": "",
      "special_service": [],
      "flight_shop": [],
      "id": 14
    },
    {
      "flightId": "2",
      "first_name": "Deepak",
      "last_name": "Sharma",
      "date_of_birth": "1/1/1998",
      "gender": "Male",
      "email_id": "deepak@sharma.com",
      "mobile_no": "876546786",
      "country": "PAK",
      "date_of_travel": "",
      "seat_no": "3D",
      "travel_document": "",
      "wheelChair": "Yes",
      "infant": "No",
      "status": "AC",
      "meals": [
        "Burger",
        "Pizza"
      ],
      "special_service": [
        "Window Seat",
        "TV"
      ],
      "flight_shop": [
        "Watch",
        "Walet",
        "HeadPhone"
      ],
      "address": "Lahore, PAK",
      "id": 15
    },
    {
      "flightId": "2",
      "first_name": "Abhishek",
      "last_name": "Agr",
      "date_of_birth": "2/2/1998",
      "gender": "Male",
      "email_id": "abhi@nhi.com",
      "mobile_no": "654678654",
      "country": "China",
      "date_of_travel": "",
      "seat_no": "6D",
      "travel_document": "",
      "wheelChair": "Yes",
      "infant": "Yes",
      "status": "AC",
      "meals": [],
      "special_service": [],
      "flight_shop": [],
      "address": "Lahore, PAK",
      "id": 16
    },
    {
      "flightId": "3",
      "first_name": "Khagesh",
      "last_name": "Kumar",
      "date_of_birth": "01/01/1757",
      "gender": "Other",
      "email_id": "khagesh@mindtree.com",
      "mobile_no": "1122334455",
      "country": "South Africa",
      "date_of_travel": "",
      "seat_no": "-",
      "travel_document": "",
      "wheelChair": "Yes",
      "infant": "Yes",
      "status": "NC",
      "meals": [],
      "special_service": [
        "Extra leg room"
      ],
      "flight_shop": [
        "Watch",
        "Power bank"
      ],
      "address": "CPT, SA",
      "id": 17
    },
    {
      "flightId": "3",
      "first_name": "Bishwajit",
      "last_name": "Bal",
      "date_of_birth": "8/1/1990",
      "gender": "Male",
      "email_id": "bishwajit@gmail.com",
      "mobile_no": "8765467887",
      "country": "ind",
      "date_of_travel": "",
      "seat_no": "1A",
      "travel_document": "",
      "wheelChair": "Yes",
      "infant": "Yes",
      "status": "AC",
      "meals": [
        "Pizza",
        "Burger",
        "Coffee"
      ],
      "special_service": [],
      "flight_shop": [],
      "address": "",
      "id": 18
    },
    {
      "flightId": "3",
      "first_name": "kavi",
      "last_name": "kumar",
      "date_of_birth": "8/10/1880",
      "gender": "Male",
      "email_id": "dfsadsf!@fdsf",
      "mobile_no": "9451459870",
      "country": "IND",
      "date_of_travel": "",
      "seat_no": "-",
      "travel_document": "786546",
      "wheelChair": "No",
      "infant": "No",
      "status": "NC",
      "address": "Mathura,india",
      "meals": [],
      "special_service": [],
      "flight_shop": [],
      "id": 19
    },
    {
      "flightId": "3",
      "first_name": "Sonia",
      "last_name": "Sonia",
      "date_of_birth": "23/12/1939",
      "gender": "Male",
      "email_id": "sonia@manmohan.com",
      "mobile_no": "9451459787",
      "country": "in",
      "date_of_travel": "",
      "seat_no": "-",
      "travel_document": "897657",
      "wheelChair": "No",
      "infant": "No",
      "status": "NC",
      "address": "gahlore,ind",
      "meals": [],
      "special_service": [],
      "flight_shop": [],
      "id": 20
    },
    {
      "flightId": "3",
      "first_name": "bill-bill",
      "last_name": "Kumar",
      "date_of_birth": "01/01/2018",
      "gender": "Male",
      "email_id": "dsfasdfas@gi.ocm",
      "mobile_no": "9451459787",
      "country": "pak",
      "date_of_travel": "",
      "seat_no": "-",
      "travel_document": "8976543",
      "wheelChair": "Yes",
      "infant": "Yes",
      "status": "NC",
      "address": "Napak, pak",
      "meals": [],
      "special_service": [],
      "flight_shop": [],
      "id": 21
    },
    {
      "flightId": "3",
      "first_name": "shashi",
      "last_name": "kant",
      "date_of_birth": "",
      "gender": "Male",
      "email_id": "shashi@kumar.com",
      "mobile_no": "987658978",
      "country": "INd",
      "date_of_travel": "",
      "seat_no": "-",
      "travel_document": "",
      "status": "NC",
      "address": "",
      "meals": [],
      "special_service": [],
      "flight_shop": [],
      "id": 22
    },
    {
      "flightId": "2",
      "first_name": "bill-bill",
      "last_name": "Gandhi",
      "date_of_birth": "01/01/2018",
      "gender": "Male",
      "email_id": "sdf!@fdsa.clom",
      "mobile_no": "89765687976",
      "country": "PAK",
      "date_of_travel": "",
      "seat_no": "-",
      "travel_document": "87655789",
      "wheelChair": "No",
      "infant": "No",
      "status": "NC",
      "address": "Ishlamabad, PAK",
      "meals": [],
      "special_service": [],
      "flight_shop": [],
      "id": 23
    }
  ],
  "flightLists": [
    {
      "id": "1",
      "flightNo": "100",
      "airline": "G9",
      "departureStation": "BLR",
      "arrivalStation": "DEL",
      "departureDate": "2019-11-27T23:30:00",
      "arrivalDate": "2019-11-27T23:30:00",
      "meals": [
        "Pizza",
        "Tea"
      ],
      "special_service": [
        "TV",
        "Music",
        "Window Seat"
      ],
      "flight_shop": [
        "Watch",
        "Walet"
      ]
    },
    {
      "id": "2",
      "flightNo": "101",
      "airline": "AI",
      "departureStation": "SHJ",
      "arrivalStation": "DEL",
      "departureDate": "2019-11-27T23:30:00",
      "arrivalDate": "2019-11-27T23:30:00",
      "meals": [
        "Pizza",
        "Burger",
        "Tea"
      ],
      "special_service": [
        "Window Seat",
        "TV",
        "Dance"
      ],
      "flight_shop": [
        "Walet",
        "Watch",
        "HeadPhone"
      ]
    },
    {
      "id": "3",
      "flightNo": "103",
      "airline": "J2",
      "departureStation": "HYD",
      "arrivalStation": "DEL",
      "departureDate": "2019-11-27T23:30:00",
      "arrivalDate": "2019-11-27T23:30:00",
      "meals": [
        "Pizza",
        "Burger",
        "Coffee"
      ],
      "special_service": [
        "Window Seat",
        "Extra leg room",
        "TV"
      ],
      "flight_shop": [
        "Watch",
        "Power bank",
        "Head phone"
      ]
    }
  ],
  "travelDocument": [
    {
      "passanger-Id": 1,
      "firstName": "Bill",
      "lastName": "Gates",
      "type-Of-Travel": "international",
      "date-Of-Birth": "3-Aug-1967",
      "address": "road num-121,banjarahills",
      "type-of-TravelDocument": "Passport",
      "document-Number": 324343216386782
    },
    {
      "passanger-Id": 2,
      "firstName": "Mark",
      "lastName": "zuckerberg",
      "type-Of-Travel": "domestic",
      "date-Of-Birth": "3-Aug-1967",
      "address": "road num-121,banjarahills",
      "type-Of-TavelDocument": "Aadhar",
      "document-Number": 324343216386782
    }
  ]
}